hexia_parameters/__init__.py
hexia_parameters/admin.py
hexia_parameters/apps.py
hexia_parameters/config.py
hexia_parameters/context_processors.py
hexia_parameters/models.py
hexia_parameters/tests.py
hexia_parameters/views.py
hexia_parameters/management/__init__.py
hexia_parameters/management/commands/__init__.py
hexia_parameters/management/commands/initialise_hexia_parameters.py
hexia_parameters/migrations/0001_initial.py
hexia_parameters/migrations/__init__.py
hexia_parameters-1.0.0.dist-info/DESCRIPTION.rst
hexia_parameters-1.0.0.dist-info/METADATA
hexia_parameters-1.0.0.dist-info/RECORD
hexia_parameters-1.0.0.dist-info/WHEEL
hexia_parameters-1.0.0.dist-info/metadata.json
hexia_parameters-1.0.0.dist-info/top_level.txt
