Metadata-Version: 2.0
Name: hexia-parameters
Version: 1.0.0
Summary: A simple Django Parameter app.
Home-page: https://github.com/HenryMehta/hexia-parameters
Author: Henry Mehta
Author-email: hjsmehta@gmail.com
License: MIT License
Keywords: django parameter app
Platform: UNKNOWN
Classifier: Environment :: Web Environment
Classifier: Framework :: Django
Classifier: Framework :: Django :: 2.0
Classifier: Intended Audience :: Developers
Classifier: License :: OSI Approved :: MIT License
Classifier: Operating System :: OS Independent
Classifier: Programming Language :: Python
Classifier: Programming Language :: Python :: 3.5
Classifier: Topic :: Internet :: WWW/HTTP
Classifier: Topic :: Internet :: WWW/HTTP :: Dynamic Content
